enigma_simulator/__init__.py
enigma_simulator/components.py
enigma_simulator/enigma.py
enigma_simulator/utils.py
enigma_simulator-0.4.0.dist-info/LICENSE
enigma_simulator-0.4.0.dist-info/METADATA
enigma_simulator-0.4.0.dist-info/WHEEL
enigma_simulator-0.4.0.dist-info/top_level.txt
enigma_simulator-0.4.0.dist-info/RECORD
