Metadata-Version: 2.1
Name: enigma-simulator
Version: 0.4.0
Summary: An implementation of the Enigma machine in Python.
Home-page: https://github.com/tristan-jl/enigma_simulator
Author: Tristan Laurens
Author-email: tristanlaurens@hotmail.com
License: MIT
Platform: UNKNOWN
Classifier: License :: OSI Approved :: MIT License
Classifier: Programming Language :: Python :: 3
Classifier: Programming Language :: Python :: 3 :: Only
Classifier: Programming Language :: Python :: 3.7
Classifier: Programming Language :: Python :: 3.8
Classifier: Programming Language :: Python :: 3.9
Classifier: Programming Language :: Python :: Implementation :: CPython
Requires-Python: >=3.7.0
Requires-Dist: numpy
